{
"autoplayBgm":true,"autoplayBgs":false,"battleback1Name":"","battleback2Name":"","bgm":{"name":"","pan":0,"pitch":100,"volume":30},"bgs":{"name":"","pan":0,"pitch":100,"volume":90},"disableDashing":false,"displayName":"CISO Office","encounterList":[],"encounterStep":30,"height":7,"note":"","parallaxLoopX":false,"parallaxLoopY":false,"parallaxName":"","parallaxShow":true,"parallaxSx":0,"parallaxSy":0,"scrollType":0,"specifyBattleback":false,"tilesetId":7,"width":7,
"data":[5988,6012,6012,6012,6012,6012,5992,6008,7914,7918,1552,7915,7914,6000,6008,4146,4132,4132,4132,4148,6000,6008,4128,4112,4112,4112,4136,6000,6008,4128,4112,4112,4112,4136,6000,6008,4152,4140,4140,4140,4150,6000,5986,6004,6004,6004,6004,6004,5985,0,0,0,0,0,0,0,0,0,0,0,0,0,0,0,0,0,0,0,0,0,0,0,0,0,0,0,0,0,0,0,0,0,0,0,0,0,0,0,0,0,0,0,0,0,0,0,0,0,0,0,0,0,0,0,0,0,0,0,0,0,0,0,0,0,0,0,0,0,0,0,0,0,0,0,0,0,0,0,0,116,0,0,0,0,0,0,0,0,0,0,0,0,0,0,0,0,0,0,0,0,0,0,0,0,0,0,0,0,0,0,0,0,0,0,0,0,0,0,0,0,0,0,0,0,0,0,0,0,112,113,0,0,0,0,0,0,0,0,0,0,0,0,0,0,0,0,0,0,0,0,0,0,0,0,0,0,5,0,0,0,0,5,0,0,0,0,0,0,5,0,0,0,0,0,0,5,0,0,0,0,0,0,5,0,0,0,0,0,0,0,0,0,0,0,0,0,0,0,0,0,0,0,0,0,0,0,0,0,0,0,0,0,0,0,0,0,0,0,0,0,0,0,0,0,0,0,0,0,0,0,0,0,0,0,0,0,0,0,0,0,0,0,0,0],
"events":[
null,
{"id":1,"name":"CynthiaD","note":"Cynthia_Delgado_CISO","pages":[{"conditions":{"actorId":1,"actorValid":false,"itemId":1,"itemValid":false,"selfSwitchCh":"A","selfSwitchValid":false,"switch1Id":1,"switch1Valid":false,"switch2Id":1,"switch2Valid":false,"variableId":1,"variableValid":false,"variableValue":1},"directionFix":false,"image":{"tileId":0,"characterName":"Actor3","direction":8,"pattern":0,"characterIndex":3},"list":[{"code":101,"indent":0,"parameters":["Actor3",3,0,2,"CISO"]},{"code":401,"indent":0,"parameters":["Great! You’re here. I wanted to start you in my office to go over what I hired you for."]},{"code":101,"indent":0,"parameters":["Actor3",3,0,2,"Cynthia Delgado"]},{"code":401,"indent":0,"parameters":["Let’s get acquainted first. My name is Cynthia Delgado, and I’m the CISO here at Tucker and Solano Law Offices. As you probably know, we cater to very high-profile clients—celebrities, politicians, CEOs. Privacy is everything to them, but lately, we’ve had leaks. Big ones."]},{"code":102,"indent":0,"parameters":[["I'm here to help","How bad is it?","Remain silent"],1,0,2,0]},{"code":402,"indent":0,"parameters":[0,"I'm here to help"]},{"code":101,"indent":1,"parameters":["Actor3",3,0,2,""]},{"code":401,"indent":1,"parameters":["Great!!"]},{"code":0,"indent":1,"parameters":[]},{"code":402,"indent":0,"parameters":[1,"How bad is it?"]},{"code":101,"indent":1,"parameters":["Actor3",3,0,2,"Cynthia Delgado"]},{"code":401,"indent":1,"parameters":["Bad enough that I’m out of a job if we don’t fix this. Someone inside the firm is feeding information to the media, and the partners are losing their patience. That’s where you come in."]},{"code":0,"indent":1,"parameters":[]},{"code":402,"indent":0,"parameters":[2,"Remain silent"]},{"code":101,"indent":1,"parameters":["MainCharacter",0,0,2,""]},{"code":401,"indent":1,"parameters":["...."]},{"code":0,"indent":1,"parameters":[]},{"code":404,"indent":0,"parameters":[]},{"code":101,"indent":0,"parameters":["Actor3",3,0,2,"Cynthia Delgado"]},{"code":401,"indent":0,"parameters":["Your expertise in behavioral cybersecurity makes you the perfect candidate to find out who’s behind this. But this is a sensitive matter—we can’t risk anyone knowing your real mission. You’ll be starting today as a microcomputer specialist in the IT office."]},{"code":102,"indent":0,"parameters":[["What's my cover story?","Understood.","This will be interesting."],1,0,2,0]},{"code":402,"indent":0,"parameters":[0,"What's my cover story?"]},{"code":101,"indent":1,"parameters":["Actor3",3,0,2,"Cynthia Delgado"]},{"code":401,"indent":1,"parameters":["Okay!  Well, your name is......"]},{"code":303,"indent":1,"parameters":[1,15]},{"code":0,"indent":1,"parameters":[]},{"code":402,"indent":0,"parameters":[1,"Understood."]},{"code":101,"indent":1,"parameters":["Actor3",3,0,2,"Cynthia Delgado"]},{"code":401,"indent":1,"parameters":["Perfect.  Your name is....."]},{"code":303,"indent":1,"parameters":[1,15]},{"code":0,"indent":1,"parameters":[]},{"code":402,"indent":0,"parameters":[2,"This will be interesting."]},{"code":101,"indent":1,"parameters":["Actor3",3,0,2,"Cynthia Delgado"]},{"code":401,"indent":1,"parameters":["Alright. Time to work on your cover story.  Your name is....."]},{"code":303,"indent":1,"parameters":[1,15]},{"code":0,"indent":1,"parameters":[]},{"code":404,"indent":0,"parameters":[]},{"code":101,"indent":0,"parameters":["Actor3",3,0,2,"Cynthia Delgado"]},{"code":401,"indent":0,"parameters":["Your cover is simple—you’re new here, hired to help with day-to-day IT issues. I’ve set up your credentials and workstation already. You’ll report directly to me when you find anything suspicious."]},{"code":126,"indent":0,"parameters":[2,0,0,1]},{"code":101,"indent":0,"parameters":["Actor3",3,0,2,"Cynthia Delgado"]},{"code":401,"indent":0,"parameters":["Here is your keycard.  Any questions before I send you to meet Troy Bennington in IT?"]},{"code":101,"indent":0,"parameters":["",0,0,2,""]},{"code":401,"indent":0,"parameters":["You got your \\C[11]keycard\\C[0] and credentials!!"]},{"code":113,"indent":0,"parameters":[]},{"code":122,"indent":0,"parameters":[1,1,0,0,1]},{"code":0,"indent":0,"parameters":[]}],"moveFrequency":3,"moveRoute":{"list":[{"code":0,"parameters":[]}],"repeat":true,"skippable":false,"wait":false},"moveSpeed":3,"moveType":0,"priorityType":1,"stepAnime":false,"through":false,"trigger":0,"walkAnime":true},{"conditions":{"actorId":1,"actorValid":false,"itemId":1,"itemValid":false,"selfSwitchCh":"A","selfSwitchValid":false,"switch1Id":1,"switch1Valid":false,"switch2Id":1,"switch2Valid":false,"variableId":1,"variableValid":true,"variableValue":1},"directionFix":false,"image":{"tileId":0,"characterName":"Actor3","direction":8,"pattern":2,"characterIndex":3},"list":[{"code":101,"indent":0,"parameters":["Actor3",3,0,2,"Cynthia Delgado"]},{"code":401,"indent":0,"parameters":["Good. Time is of the essence, so I suggest you get started. Troy’s expecting you"]},{"code":0,"indent":0,"parameters":[]}],"moveFrequency":3,"moveRoute":{"list":[{"code":0,"parameters":[]}],"repeat":true,"skippable":false,"wait":false},"moveSpeed":3,"moveType":0,"priorityType":1,"stepAnime":false,"through":false,"trigger":0,"walkAnime":true},{"conditions":{"actorId":1,"actorValid":false,"itemId":1,"itemValid":false,"selfSwitchCh":"A","selfSwitchValid":false,"switch1Id":1,"switch1Valid":false,"switch2Id":1,"switch2Valid":false,"variableId":20,"variableValid":true,"variableValue":2},"directionFix":false,"image":{"tileId":0,"characterName":"Actor3","direction":8,"pattern":0,"characterIndex":3},"list":[{"code":101,"indent":0,"parameters":["Actor3",3,0,0,"Cynthia"]},{"code":401,"indent":0,"parameters":["I’ve reviewed your work so far—impressive. But don’t let your guard down. The phishing attempt you stopped might be a coincidence, or it could be a sign we’re getting closer to the culprit."]},{"code":102,"indent":0,"parameters":[["What's the next move?","Should i start monitoring suspects?","Do you thnk someone's testing us?"],1,0,2,0]},{"code":402,"indent":0,"parameters":[0,"What's the next move?"]},{"code":0,"indent":1,"parameters":[]},{"code":402,"indent":0,"parameters":[1,"Should i start monitoring suspects?"]},{"code":0,"indent":1,"parameters":[]},{"code":402,"indent":0,"parameters":[2,"Do you thnk someone's testing us?"]},{"code":0,"indent":1,"parameters":[]},{"code":404,"indent":0,"parameters":[]},{"code":101,"indent":0,"parameters":["Actor3",3,0,0,"Cynthia"]},{"code":401,"indent":0,"parameters":["For now, keep investigating and report anything unusual. Trust no one, not even me."]},{"code":122,"indent":0,"parameters":[1,1,0,0,2]},{"code":221,"indent":0,"parameters":[]},{"code":230,"indent":0,"parameters":[60]},{"code":201,"indent":0,"parameters":[0,9,2,4,8,0]},{"code":222,"indent":0,"parameters":[]},{"code":121,"indent":0,"parameters":[19,19,0]},{"code":0,"indent":0,"parameters":[]}],"moveFrequency":3,"moveRoute":{"list":[{"code":0,"parameters":[]}],"repeat":true,"skippable":false,"wait":false},"moveSpeed":3,"moveType":0,"priorityType":1,"stepAnime":false,"through":false,"trigger":0,"walkAnime":true},{"conditions":{"actorId":1,"actorValid":false,"itemId":1,"itemValid":false,"selfSwitchCh":"A","selfSwitchValid":false,"switch1Id":19,"switch1Valid":true,"switch2Id":1,"switch2Valid":false,"variableId":1,"variableValid":false,"variableValue":0},"directionFix":false,"image":{"tileId":0,"characterName":"Actor3","direction":8,"pattern":0,"characterIndex":3},"list":[{"code":101,"indent":0,"parameters":["Actor3",3,0,0,"Cynthia"]},{"code":401,"indent":0,"parameters":["Your work so far has been solid, but this is where things get tricky. The phishing attack in Criminal wasn’t random—it’s part of a pattern. I’ve flagged unusual activity across departments. You’ll need to visit them, solve their issues, and dig for clues while keeping up appearances"]},{"code":101,"indent":0,"parameters":["MainCharacter",0,0,2,"\\N[1]"]},{"code":401,"indent":0,"parameters":["OK"]},{"code":102,"indent":0,"parameters":[["Which departments?","What kind of activity?","What kind of activity?"],1,0,2,0]},{"code":402,"indent":0,"parameters":[0,"Which departments?"]},{"code":0,"indent":1,"parameters":[]},{"code":402,"indent":0,"parameters":[1,"What kind of activity?"]},{"code":0,"indent":1,"parameters":[]},{"code":402,"indent":0,"parameters":[2,"What kind of activity?"]},{"code":0,"indent":1,"parameters":[]},{"code":404,"indent":0,"parameters":[]},{"code":101,"indent":0,"parameters":["Actor3",3,0,0,"Cynthia"]},{"code":401,"indent":0,"parameters":["Start with Labor & Employment. There have been multiple complaints about slow systems and missing files. Be discreet—anything you find, bring it straight to me"]},{"code":0,"indent":0,"parameters":[]}],"moveFrequency":3,"moveRoute":{"list":[{"code":0,"parameters":[]}],"repeat":true,"skippable":false,"wait":false},"moveSpeed":3,"moveType":0,"priorityType":1,"stepAnime":false,"through":false,"trigger":0,"walkAnime":true}],"x":3,"y":5},
{"id":2,"name":"CISO>ITOffice","note":"","pages":[{"conditions":{"actorId":1,"actorValid":false,"itemId":1,"itemValid":false,"selfSwitchCh":"A","selfSwitchValid":false,"switch1Id":1,"switch1Valid":false,"switch2Id":1,"switch2Valid":false,"variableId":1,"variableValid":false,"variableValue":0},"directionFix":false,"image":{"tileId":0,"characterName":"!Door1","direction":2,"pattern":2,"characterIndex":4},"list":[{"code":111,"indent":0,"parameters":[1,1,0,1,4]},{"code":101,"indent":1,"parameters":["",0,0,2,""]},{"code":401,"indent":1,"parameters":["Please speak with your new \\c[2]CISO\\c[0]"]},{"code":0,"indent":1,"parameters":[]},{"code":411,"indent":0,"parameters":[]},{"code":250,"indent":1,"parameters":[{"name":"Open1","volume":90,"pitch":100,"pan":0}]},{"code":205,"indent":1,"parameters":[0,{"repeat":false,"skippable":false,"wait":true,"list":[{"code":17},{"code":15,"parameters":[3]},{"code":18},{"code":15,"parameters":[3]},{"code":19},{"code":37},{"code":0}]}]},{"code":505,"indent":1,"parameters":[{"code":17}]},{"code":505,"indent":1,"parameters":[{"code":15,"parameters":[3]}]},{"code":505,"indent":1,"parameters":[{"code":18}]},{"code":505,"indent":1,"parameters":[{"code":15,"parameters":[3]}]},{"code":505,"indent":1,"parameters":[{"code":19}]},{"code":505,"indent":1,"parameters":[{"code":37}]},{"code":205,"indent":1,"parameters":[-1,{"repeat":false,"skippable":true,"wait":true,"list":[{"code":12},{"code":0}]}]},{"code":505,"indent":1,"parameters":[{"code":12}]},{"code":201,"indent":1,"parameters":[0,2,3,9,0,0]},{"code":250,"indent":1,"parameters":[{"name":"Move1","volume":90,"pitch":100,"pan":0}]},{"code":0,"indent":1,"parameters":[]},{"code":412,"indent":0,"parameters":[]},{"code":0,"indent":0,"parameters":[]}],"moveFrequency":3,"moveRoute":{"list":[{"code":0,"parameters":[]}],"repeat":true,"skippable":false,"wait":false},"moveSpeed":3,"moveType":0,"priorityType":1,"stepAnime":false,"through":false,"trigger":1,"walkAnime":false},{"conditions":{"actorId":1,"actorValid":false,"itemId":1,"itemValid":false,"selfSwitchCh":"A","selfSwitchValid":false,"switch1Id":1,"switch1Valid":false,"switch2Id":1,"switch2Valid":false,"variableId":1,"variableValid":true,"variableValue":2},"directionFix":false,"image":{"tileId":0,"characterName":"!Door1","direction":2,"pattern":2,"characterIndex":4},"list":[{"code":111,"indent":0,"parameters":[1,1,0,1,4]},{"code":101,"indent":1,"parameters":["",0,0,2,""]},{"code":401,"indent":1,"parameters":["Please speak with your new \\c[2]CISO\\c[0]"]},{"code":0,"indent":1,"parameters":[]},{"code":411,"indent":0,"parameters":[]},{"code":250,"indent":1,"parameters":[{"name":"Open1","volume":90,"pitch":100,"pan":0}]},{"code":205,"indent":1,"parameters":[0,{"repeat":false,"skippable":false,"wait":true,"list":[{"code":17},{"code":15,"parameters":[3]},{"code":18},{"code":15,"parameters":[3]},{"code":19},{"code":37},{"code":0}]}]},{"code":505,"indent":1,"parameters":[{"code":17}]},{"code":505,"indent":1,"parameters":[{"code":15,"parameters":[3]}]},{"code":505,"indent":1,"parameters":[{"code":18}]},{"code":505,"indent":1,"parameters":[{"code":15,"parameters":[3]}]},{"code":505,"indent":1,"parameters":[{"code":19}]},{"code":505,"indent":1,"parameters":[{"code":37}]},{"code":205,"indent":1,"parameters":[-1,{"repeat":false,"skippable":true,"wait":true,"list":[{"code":12},{"code":0}]}]},{"code":505,"indent":1,"parameters":[{"code":12}]},{"code":201,"indent":1,"parameters":[0,9,3,9,0,0]},{"code":250,"indent":1,"parameters":[{"name":"Move1","volume":90,"pitch":100,"pan":0}]},{"code":0,"indent":1,"parameters":[]},{"code":412,"indent":0,"parameters":[]},{"code":0,"indent":0,"parameters":[]}],"moveFrequency":3,"moveRoute":{"list":[{"code":0,"parameters":[]}],"repeat":true,"skippable":false,"wait":false},"moveSpeed":3,"moveType":0,"priorityType":1,"stepAnime":false,"through":false,"trigger":0,"walkAnime":true},{"conditions":{"actorId":1,"actorValid":false,"itemId":1,"itemValid":false,"selfSwitchCh":"A","selfSwitchValid":false,"switch1Id":19,"switch1Valid":true,"switch2Id":1,"switch2Valid":false,"variableId":1,"variableValid":true,"variableValue":2},"directionFix":false,"image":{"tileId":0,"characterName":"!Door1","direction":2,"pattern":2,"characterIndex":4},"list":[{"code":111,"indent":0,"parameters":[1,1,0,1,4]},{"code":101,"indent":1,"parameters":["",0,0,2,""]},{"code":401,"indent":1,"parameters":["Please speak with your new \\c[2]CISO\\c[0]"]},{"code":0,"indent":1,"parameters":[]},{"code":411,"indent":0,"parameters":[]},{"code":250,"indent":1,"parameters":[{"name":"Open1","volume":90,"pitch":100,"pan":0}]},{"code":205,"indent":1,"parameters":[0,{"repeat":false,"skippable":false,"wait":true,"list":[{"code":17},{"code":15,"parameters":[3]},{"code":18},{"code":15,"parameters":[3]},{"code":19},{"code":37},{"code":0}]}]},{"code":505,"indent":1,"parameters":[{"code":17}]},{"code":505,"indent":1,"parameters":[{"code":15,"parameters":[3]}]},{"code":505,"indent":1,"parameters":[{"code":18}]},{"code":505,"indent":1,"parameters":[{"code":15,"parameters":[3]}]},{"code":505,"indent":1,"parameters":[{"code":19}]},{"code":505,"indent":1,"parameters":[{"code":37}]},{"code":205,"indent":1,"parameters":[-1,{"repeat":false,"skippable":true,"wait":true,"list":[{"code":12},{"code":0}]}]},{"code":505,"indent":1,"parameters":[{"code":12}]},{"code":201,"indent":1,"parameters":[0,9,3,9,0,0]},{"code":250,"indent":1,"parameters":[{"name":"Move1","volume":90,"pitch":100,"pan":0}]},{"code":0,"indent":1,"parameters":[]},{"code":412,"indent":0,"parameters":[]},{"code":0,"indent":0,"parameters":[]}],"moveFrequency":3,"moveRoute":{"list":[{"code":0,"parameters":[]}],"repeat":true,"skippable":false,"wait":false},"moveSpeed":3,"moveType":0,"priorityType":1,"stepAnime":false,"through":false,"trigger":0,"walkAnime":true}],"x":3,"y":1},
null
]
}